LICENSE
MANIFEST.in
README.md
requirements.txt
setup.py
browserctrl/__init__.py
browserctrl/app.py
browserctrl/browser.py
browserctrl/run.py
browserctrl/template.py
browserctrl.egg-info/PKG-INFO
browserctrl.egg-info/SOURCES.txt
browserctrl.egg-info/dependency_links.txt
browserctrl.egg-info/entry_points.txt
browserctrl.egg-info/requires.txt
browserctrl.egg-info/top_level.txt